silobuster/LICENSE
silobuster/README.md
silobuster/__init__.py
silobuster/libs/__init__.py
silobuster/libs/uuid.py
silobuster/libs/ARCHIVED/deduplication_results.csv
silobuster/libs/ARCHIVED/connectors/abstract_connector.py
silobuster/libs/ARCHIVED/connectors/postgres_connector.py
silobuster/libs/ARCHIVED/connectors/test_conn.ipynb
silobuster/libs/ARCHIVED/connectors/.ipynb_checkpoints/test_conn-checkpoint.ipynb
silobuster/libs/ARCHIVED/connectors/__pycache__/abstract_connector.cpython-310.pyc
silobuster/libs/ARCHIVED/connectors/__pycache__/abstract_connector.cpython-36.pyc
silobuster/libs/ARCHIVED/connectors/__pycache__/abstract_connector.cpython-39.pyc
silobuster/libs/ARCHIVED/connectors/__pycache__/postgres_connector.cpython-310.pyc
silobuster/libs/ARCHIVED/connectors/__pycache__/postgres_connector.cpython-36.pyc
silobuster/libs/ARCHIVED/connectors/__pycache__/postgres_connector.cpython-39.pyc
silobuster/libs/ARCHIVED/feeds/abstract_feed.py
silobuster/libs/ARCHIVED/feeds/postgres_feed.py
silobuster/libs/ARCHIVED/feeds/test.txt
silobuster/libs/ARCHIVED/feeds/__pycache__/abstract_feed.cpython-310.pyc
silobuster/libs/ARCHIVED/feeds/__pycache__/abstract_feed.cpython-39.pyc
silobuster/libs/ARCHIVED/feeds/__pycache__/postgres_feed.cpython-310.pyc
silobuster/libs/ARCHIVED/feeds/__pycache__/postgres_feed.cpython-39.pyc
silobuster/libs/__pycache__/uuid.cpython-310.pyc
silobuster/libs/base_classes/base_iterator.py
silobuster/libs/base_classes/singleton.py
silobuster/libs/base_classes/__pycache__/base_iterator.cpython-310.pyc
silobuster/libs/base_classes/__pycache__/singleton.cpython-310.pyc
silobuster/libs/connector/base_connector.py
silobuster/libs/connector/dataframe_connector.py
silobuster/libs/connector/generic_connector.py
silobuster/libs/connector/postgres_connector.py
silobuster/libs/connector/__pycache__/base_connector.cpython-310.pyc
silobuster/libs/connector/__pycache__/base_converter.cpython-310.pyc
silobuster-1.0.3.dist-info/METADATA
silobuster-1.0.3.dist-info/WHEEL
silobuster-1.0.3.dist-info/top_level.txt
silobuster-1.0.3.dist-info/RECORD
